macos_gemini_overlay/.DS_Store
macos_gemini_overlay/__init__.py
macos_gemini_overlay/__main__.py
macos_gemini_overlay/app.py
macos_gemini_overlay/constants.py
macos_gemini_overlay/health_checks.py
macos_gemini_overlay/launcher.py
macos_gemini_overlay/listener.py
macos_gemini_overlay/main.py
macos_gemini_overlay/__pycache__/__init__.cpython-312.pyc
macos_gemini_overlay/__pycache__/app.cpython-312.pyc
macos_gemini_overlay/__pycache__/constants.cpython-312.pyc
macos_gemini_overlay/__pycache__/health_checks.cpython-312.pyc
macos_gemini_overlay/__pycache__/launcher.cpython-312.pyc
macos_gemini_overlay/__pycache__/listener.cpython-312.pyc
macos_gemini_overlay/__pycache__/main.cpython-312.pyc
macos_gemini_overlay/about/author.txt
macos_gemini_overlay/about/classifiers.txt
macos_gemini_overlay/about/description.txt
macos_gemini_overlay/about/keywords.txt
macos_gemini_overlay/about/on_pypi.txt
macos_gemini_overlay/about/package_name.txt
macos_gemini_overlay/about/requirements.txt
macos_gemini_overlay/about/version.txt
macos_gemini_overlay/about/version_history.md
macos_gemini_overlay/logo/.DS_Store
macos_gemini_overlay/logo/icon.icns
macos_gemini_overlay/logo/logo_black.png
macos_gemini_overlay/logo/logo_white.png
macos_gemini_overlay/logo/icon.iconset/.DS_Store
macos_gemini_overlay/logo/icon.iconset/icon_1024x1024.png
macos_gemini_overlay/logo/icon.iconset/icon_128x128.png
macos_gemini_overlay/logo/icon.iconset/icon_128x128@2x.png
macos_gemini_overlay/logo/icon.iconset/icon_16x16.png
macos_gemini_overlay/logo/icon.iconset/icon_16x16@2x.png
macos_gemini_overlay/logo/icon.iconset/icon_256x256.png
macos_gemini_overlay/logo/icon.iconset/icon_256x256@2x.png
macos_gemini_overlay/logo/icon.iconset/icon_32x32.png
macos_gemini_overlay/logo/icon.iconset/icon_32x32@2x.png
macos_gemini_overlay/logo/icon.iconset/icon_512x512.png
macos_gemini_overlay/logo/icon.iconset/icon_512x512@2x.png
macos_gemini_overlay/logo/icon.iconset/icon_64x64.png
macos_gemini_overlay-0.0.3.dist-info/licenses/LICENSE
macos_gemini_overlay-0.0.3.dist-info/METADATA
macos_gemini_overlay-0.0.3.dist-info/WHEEL
macos_gemini_overlay-0.0.3.dist-info/entry_points.txt
macos_gemini_overlay-0.0.3.dist-info/top_level.txt
macos_gemini_overlay-0.0.3.dist-info/RECORD
