Metadata-Version: 2.4
Name: macos_gemini_overlay
Version: 0.0.3
Summary: A simple macOS overlay application for pinning 'gemini.google.com' to a dedicated window and key command.
Home-page: https://github.com/jzelenkov/macos_gemini_overlay
Download-URL: https://github.com/jzelenkov/macos_gemini_overlay/archive/0.0.3.tar.gz
Author: Jay Zelenkov
Author-email: jay.zelenkov@gmail.com
License: MIT
Keywords: python3,gemini,macos
Classifier: Operating System :: MacOS
Classifier: Development Status :: 5 - Production/Stable
Classifier: License :: OSI Approved :: MIT License
Classifier: Programming Language :: Python :: 3
Classifier: Programming Language :: Python :: 3.13
Requires-Python: >=3.10
License-File: LICENSE
Requires-Dist: pyobjc
Dynamic: author
Dynamic: author-email
Dynamic: classifier
Dynamic: download-url
Dynamic: home-page
Dynamic: keywords
Dynamic: license
Dynamic: license-file
Dynamic: requires-dist
Dynamic: requires-python
Dynamic: summary
